idec/__init__.py
idec/dec.py
idec-0.0.1.dist-info/LICENSE
idec-0.0.1.dist-info/METADATA
idec-0.0.1.dist-info/WHEEL
idec-0.0.1.dist-info/top_level.txt
idec-0.0.1.dist-info/RECORD
